Metadata-Version: 2.1
Name: turbosmsua-python3
Version: 0.4.1
Summary: Client for https://turbosms.ua
Home-page: https://github.com/aorzh/turbosmsua
Author: Oleksii Orzeshkovskyi
Author-email: al.orzh@gmail.com
License: UNKNOWN
Keywords: turbosmsua,turbosms,sms ua
Platform: UNKNOWN
License-File: LICENSE.txt
